snapthon/__init__.py
snapthon-0.0.1.dist-info/LICENSES.txt
snapthon-0.0.1.dist-info/METADATA
snapthon-0.0.1.dist-info/WHEEL
snapthon-0.0.1.dist-info/top_level.txt
snapthon-0.0.1.dist-info/RECORD
