Metadata-Version: 2.1
Name: snapthon
Version: 0.0.1
Summary: This package can make simple snapchat task get user info, stories downloader 
Author: 01270
Author-email: <mail@noemail.com>
Keywords: snapchat,stories downloader
Classifier: Development Status :: 1 - Planning
Classifier: Intended Audience :: Developers
Classifier: Programming Language :: Python :: 3
Classifier: Operating System :: Unix
Classifier: Operating System :: MacOS :: MacOS X
Classifier: Operating System :: Microsoft :: Windows
License-File: LICENSES.txt
Requires-Dist: requests
